qiuyue_mcp_uvx/__init__.py
qiuyue_mcp_uvx-0.1.0.dist-info/WHEEL
qiuyue_mcp_uvx-0.1.0.dist-info/entry_points.txt
qiuyue_mcp_uvx-0.1.0.dist-info/METADATA
qiuyue_mcp_uvx-0.1.0.dist-info/RECORD
